santa/__init__.py
santa/cli.py
santa/context_processor.py
santa/extractor.py
santa/loader.py
santa/shell.py
santa/suite.py
santa/task.py
santa/tasks.py
santa/validator.py
santa/builtins/__init__.py
santa/builtins/context_processors.py
santa/builtins/extractors.py
santa/builtins/fields.py
santa/builtins/render.py
santa/builtins/tasks.py
santa/builtins/validators.py
santa/context/__init__.py
santa/parser/__init__.py
santa_rest_test-0.1.0.dist-info/LICENSE
santa_rest_test-0.1.0.dist-info/METADATA
santa_rest_test-0.1.0.dist-info/WHEEL
santa_rest_test-0.1.0.dist-info/entry_points.txt
santa_rest_test-0.1.0.dist-info/top_level.txt
santa_rest_test-0.1.0.dist-info/RECORD
