Metadata-Version: 2.1
Name: santa-rest-test
Version: 0.1.0
Summary: Easy API testing.
Home-page: https://github.com/lisael/santa
Author: Bruno Dupuis
Author-email: lisael@lisael.org
License: GNU General Public License v3
Keywords: santa
Platform: UNKNOWN
Classifier: Development Status :: 2 - Pre-Alpha
Classifier: Intended Audience :: Developers
Classifier: License :: OSI Approved :: GNU General Public License v3 (GPLv3)
Classifier: Natural Language :: English
Classifier: Programming Language :: Python :: 3.6
Requires-Dist: Click (>=6.0)
Requires-Dist: pyaml
Requires-Dist: Jinja2
Requires-Dist: jq
Requires-Dist: aiohttp
Requires-Dist: ruamel.yaml
